MANIFEST.in
setup.cfg
setup.py
dyck/MCFParser.py
dyck/__init__.py
dyck/__main__.py
dyck/dyck.py
dyck/grammar_utils.py
dyck.egg-info/PKG-INFO
dyck.egg-info/SOURCES.txt
dyck.egg-info/dependency_links.txt
dyck.egg-info/entry_points.txt
dyck.egg-info/requires.txt
dyck.egg-info/top_level.txt
dyck/grammars/__init__.py
dyck/grammars/aris1.py
dyck/grammars/aris2.py
dyck/grammars/aris3.py
dyck/grammars/meta1.py
dyck/grammars/meta2.py
dyck/grammars/meta3.py
dyck/grammars/meta4.py
dyck/grammars/triple_insertion.py