Metadata-Version: 1.0
Name: dyck
Version: 0.3.0
Summary: Meta-grammar utilities for multi-dimensional Dyck languages.
Home-page: http://github.com/omelkonian/dyck
Author: Orestis Melkonian, Konstantinos Kogkalidis
Author-email: melkon.or@gmail.com, konstantinos@riseup.net
License: UNKNOWN
Platform: any
